accelbyte_py_sdk/api/group/__init__.py
accelbyte_py_sdk/api/group/errors.py
accelbyte_py_sdk/api/group/models/__init__.py
accelbyte_py_sdk/api/group/models/models_assign_role_to_member_request_v1.py
accelbyte_py_sdk/api/group/models/models_cancel_invitation_group_response_v2.py
accelbyte_py_sdk/api/group/models/models_create_group_configuration_request_v1.py
accelbyte_py_sdk/api/group/models/models_create_group_configuration_response_v1.py
accelbyte_py_sdk/api/group/models/models_create_member_role_request_v1.py
accelbyte_py_sdk/api/group/models/models_get_group_configuration_response_v1.py
accelbyte_py_sdk/api/group/models/models_get_group_list_request_v2.py
accelbyte_py_sdk/api/group/models/models_get_group_member_list_response_v1.py
accelbyte_py_sdk/api/group/models/models_get_groups_list_response_v1.py
accelbyte_py_sdk/api/group/models/models_get_groups_response_v1.py
accelbyte_py_sdk/api/group/models/models_get_member_requests_list_response_v1.py
accelbyte_py_sdk/api/group/models/models_get_member_roles_list_response_v1.py
accelbyte_py_sdk/api/group/models/models_get_user_group_information_response_v1.py
accelbyte_py_sdk/api/group/models/models_group_member.py
accelbyte_py_sdk/api/group/models/models_group_response_v1.py
accelbyte_py_sdk/api/group/models/models_group_rule.py
accelbyte_py_sdk/api/group/models/models_group_rule_group_custom_rule.py
accelbyte_py_sdk/api/group/models/models_group_rule_response_v1.py
accelbyte_py_sdk/api/group/models/models_group_rule_response_v1_group_custom_rule.py
accelbyte_py_sdk/api/group/models/models_join_group_response_v1.py
accelbyte_py_sdk/api/group/models/models_kick_group_member_response_v1.py
accelbyte_py_sdk/api/group/models/models_leave_group_response_v1.py
accelbyte_py_sdk/api/group/models/models_list_configuration_response_v1.py
accelbyte_py_sdk/api/group/models/models_member_request_group_response_v1.py
accelbyte_py_sdk/api/group/models/models_member_request_response_v1.py
accelbyte_py_sdk_service_group-0.24.0.dist-info/METADATA
accelbyte_py_sdk_service_group-0.24.0.dist-info/WHEEL
accelbyte_py_sdk_service_group-0.24.0.dist-info/top_level.txt
accelbyte_py_sdk_service_group-0.24.0.dist-info/RECORD
