Metadata-Version: 2.4
Name: accelbyte-py-sdk-service-group
Version: 0.24.0
Summary: AccelByte Python SDK - AccelByte Gaming Services Group Service
Requires-Python: >=3.9
Requires-Dist: accelbyte-py-sdk-core
